AI_SOC/rtl/accelerator/mac.sv
`timescale 1ns/1ps

module mac #(
    parameter int DATA_WIDTH = 8,
    parameter int ACC_WIDTH  = 32
)(
    input  logic                             clk,
    input  logic                             rst_n,
    input  logic                             enable,
    input  logic                             clear,
    input  logic signed [DATA_WIDTH-1:0]     a,
    input  logic signed [DATA_WIDTH-1:0]     b,
    output logic signed [ACC_WIDTH-1:0]      acc
);

    // Explicit signed multiplication product
    logic signed [(2*DATA_WIDTH)-1:0] mult_product;

    // Signed multiplication of inputs a and b
    always_comb begin
        mult_product = a * b;
    end

    // Clocked synchronous accumulation with active-low asynchronous/synchronous reset
    always_ff @(posedge clk or negedge rst_n) begin
        if (!rst_n) begin
            acc <= '0;
        end else if (clear) begin
            acc <= '0;
        end else if (enable) begin
            // Sign-extended accumulation into 32-bit register
            acc <= acc + { {(ACC_WIDTH - 2*DATA_WIDTH){mult_product[(2*DATA_WIDTH)-1]}}, mult_product };
        end
    end

endmodule

AI_SOC/tb/tb_mac.sv
`timescale 1ns/1ps

module tb_mac;

    parameter int DATA_WIDTH = 8;
    parameter int ACC_WIDTH  = 32;

    logic                             clk;
    logic                             rst_n;
    logic                             enable;
    logic                             clear;
    logic signed [DATA_WIDTH-1:0]     a;
    logic signed [DATA_WIDTH-1:0]     b;
    logic signed [ACC_WIDTH-1:0]      acc;

    int pass_count = 0;
    int fail_count = 0;

    // Instantiate MAC module under test
    mac #(
        .DATA_WIDTH(DATA_WIDTH),
        .ACC_WIDTH(ACC_WIDTH)
    ) dut (
        .clk    (clk),
        .rst_n  (rst_n),
        .enable (enable),
        .clear  (clear),
        .a      (a),
        .b      (b),
        .acc    (acc)
    );

    // Clock Generation: 10ns period (100MHz)
    always #5 clk = ~clk;

    // Helper task to check results
    task check_result(input string test_name, input logic signed [ACC_WIDTH-1:0] expected);
        @(posedge clk);
        #1; // Sample after clock edge
        if (acc === expected) begin
            $display("[PASS] %s | Expected: %0d, Got: %0d", test_name, expected, acc);
            pass_count++;
        end else begin
            $display("[FAIL] %s | Expected: %0d, Got: %0d", test_name, expected, acc);
            fail_count++;
        end
    endtask

    initial begin
        // Setup VCD waveform dump
        $dumpfile("waves/tb_mac.vcd");
        $dumpvars(0, tb_mac);

        $display("==================================================");
        $display("          RUNNING MAC MODULE TESTBENCH            ");
        $display("==================================================");

        // Initialize signals
        clk    = 0;
        rst_n  = 0;
        enable = 0;
        clear  = 0;
        a      = 0;
        b      = 0;

        // TEST 1: Reset Behavior
        #20;
        rst_n = 1;
        check_result("TEST 1: Reset -> Acc is 0", 32'sd0);

        // TEST 2: Positive * Positive
        @(negedge clk);
        enable = 1;
        a = 8'sd5;
        b = 8'sd6;
        check_result("TEST 2: 5 * 6 = 30", 32'sd30);

        // TEST 3: Positive * Negative
        @(negedge clk);
        enable = 1;
        a = 8'sd4;
        b = -8'sd10; // 30 + (4 * -10) = 30 - 40 = -10
        check_result("TEST 3: Acc(-10) via 4 * -10", -32'sd10);

        // TEST 4: Negative * Negative
        @(negedge clk);
        enable = 1;
        a = -8'sd7;
        b = -8'sd8; // -10 + (-7 * -8) = -10 + 56 = 46
        check_result("TEST 4: Acc(46) via -7 * -8", 32'sd46);

        // TEST 5: Clear Operation
        @(negedge clk);
        enable = 0;
        clear  = 1;
        check_result("TEST 5: Clear signal -> Acc is 0", 32'sd0);

        // TEST 6: Multiple accumulated MAC operations
        @(negedge clk);
        clear  = 0;
        enable = 1;
        a = 8'sd12; b = 8'sd3;  // +36 (acc = 36)
        @(posedge clk); #1;
        a = 8'sd10; b = 8'sd10; // +100 (acc = 136)
        @(posedge clk); #1;
        a = -8'sd5; b = 8'sd6;  // -30 (acc = 106)
        check_result("TEST 6: Accumulated 3 steps -> 106", 32'sd106);

        // TEST 7: Extreme signed limits (INT8 max / min)
        @(negedge clk);
        clear = 1;
        @(negedge clk);
        clear = 0;
        enable = 1;
        a = -8'sd128; // Min signed 8-bit
        b = -8'sd128; // Min signed 8-bit -> Product is +16384
        check_result("TEST 7: Signed INT8 min * min = +16384", 32'sd16384);

        // TEST 8: Enable = 0 holds accumulator value
        @(negedge clk);
        enable = 0;
        a = 8'sd100;
        b = 8'sd100;
        check_result("TEST 8: Enable=0 holds value (16384)", 32'sd16384);

        #20;
        $display("==================================================");
        $display("MAC TEST RESULTS: %0d PASSED, %0d FAILED", pass_count, fail_count);
        $display("==================================================");

        if (fail_count == 0) begin
            $display("[ALL MAC TESTS PASSED]");
        end else begin
            $display("[MAC TESTS FAILED]");
        end

        $finish;
    end

endmodule

waves/tb_mac.vcd
$date
	Sun Aug 30 15:11:31 2026
$end
$version
	Icarus Verilog
$end
$timescale
	1ps
$end
$scope module tb_mac $end
$var wire 32 ! acc [31:0] $end
$var parameter 32 " ACC_WIDTH $end
$var parameter 32 # DATA_WIDTH $end
$var reg 8 $ a [7:0] $end
$var reg 8 % b [7:0] $end
$var reg 1 & clear $end
$var reg 1 ' clk $end
$var reg 1 ( enable $end
$var reg 1 ) rst_n $end
$var integer 32 * fail_count [31:0] $end
$var integer 32 + pass_count [31:0] $end
$scope module dut $end
$var wire 8 , a [7:0] $end
$var wire 8 - b [7:0] $end
$var wire 1 & clear $end
$var wire 1 ' clk $end
$var wire 1 ( enable $end
$var wire 1 ) rst_n $end
$var parameter 32 . ACC_WIDTH $end
$var parameter 32 / DATA_WIDTH $end
$var reg 32 0 acc [31:0] $end
$var reg 16 1 mult_product [15:0] $end
$upscope $end
$scope task check_result $end
$var reg 32 2 expected [31:0] $end
$upscope $end
$upscope $end
$enddefinitions $end
$comment Show the parameter values. $end
$dumpall
b1000 /
b100000 .
b1000 #
b100000 "
$end
#0
$dumpvars
bx 2
b0 1
b0 0
b0 -
b0 ,
b0 +
b0 *
0)
0(
0'
0&
b0 %
b0 $
b0 !
$end
#5000
1'
#10000
0'
#15000
1'
#20000
0'
b0 2
1)
#25000
1'
#26000
b1 +
#30000
b11110 1
b11110 2
b110 %
b110 -
b101 $
b101 ,
1(
0'
#35000
b11110 !
b11110 0
1'
#36000
b10 +
#40000
b1111111111011000 1
b11111111111111111111111111110110 2
b11110110 %
b11110110 -
b100 $
b100 ,
0'
#45000
b11111111111111111111111111110110 !
b11111111111111111111111111110110 0
1'
#46000
b11 +
#50000
b111000 1
b101110 2
b11111000 %
b11111000 -
b11111001 $
b11111001 ,
0'
#55000
b101110 !
b101110 0
1'
#56000
b100 +
#60000
b0 2
1&
0(
0'
#65000
b0 !
b0 0
1'
#66000
b101 +
#70000
b100100 1
b11 %
b11 -
b1100 $
b1100 ,
1(
0&
0'
#75000
b100100 !
b100100 0
1'
#76000
b1100100 1
b1010 %
b1010 -
b1010 $
b1010 ,
#80000
0'
#85000
b10001000 !
b10001000 0
1'
#86000
b1111111111100010 1
b1101010 2
b110 %
b110 -
b11111011 $
b11111011 ,
#90000
0'
#95000
b1101010 !
b1101010 0
1'
#96000
b110 +
#100000
1&
0'
#105000
b0 !
b0 0
1'
#110000
b100000000000000 1
b100000000000000 2
b10000000 %
b10000000 -
b10000000 $
b10000000 ,
0&
0'
#115000
b100000000000000 !
b100000000000000 0
1'
#116000
b111 +
#120000
b10011100010000 1
b1100100 %
b1100100 -
b1100100 $
b1100100 ,
0(
0'
#125000
1'
#126000
b1000 +
